trivoreid/__init__.py
trivoreid/client.py
trivoreid/exceptions.py
trivoreid/models/__init__.py
trivoreid/models/datastorage.py
trivoreid/models/email.py
trivoreid/models/email_template.py
trivoreid/models/enterprise.py
trivoreid/models/groups.py
trivoreid/models/invite.py
trivoreid/models/misc.py
trivoreid/models/mydata.py
trivoreid/models/namespace.py
trivoreid/models/objectid.py
trivoreid/models/page.py
trivoreid/models/pass_requirements.py
trivoreid/models/profile.py
trivoreid/models/sms.py
trivoreid/models/user.py
trivoreid/oidc/__init__.py
trivoreid/oidc/oidc_client.py
trivoreid/oidc/oidc_user.py
trivoreid/services/__init__.py
trivoreid/services/datastorage_service.py
trivoreid/services/email_service.py
trivoreid/services/email_templates_service.py
trivoreid/services/group_service.py
trivoreid/services/mydata_service.py
trivoreid/services/namespace_service.py
trivoreid/services/profile_service.py
trivoreid/services/sms_service.py
trivoreid/services/user_service.py
trivoreid/utils/__init__.py
trivoreid/utils/criteria.py
trivoreid/utils/service_utils.py
trivoreid-2.0.10.dist-info/LICENSE
trivoreid-2.0.10.dist-info/METADATA
trivoreid-2.0.10.dist-info/WHEEL
trivoreid-2.0.10.dist-info/top_level.txt
trivoreid-2.0.10.dist-info/RECORD
