Metadata-Version: 2.1
Name: trivoreid
Version: 2.0.10
Summary: Wrapper for TrivoreID SDK
Home-page: UNKNOWN
Author: Anastasia Gromova
Author-email: id-client-sdk@trivore.com
Maintainer: Anastasia Gromova
Maintainer-email: id-client-sdk@trivore.com
License: Apache 2.0
Platform: UNKNOWN
